gembatch/__init__.py
gembatch/__main__.py
gembatch/cloudbuild.yml
gembatch/configs.py
gembatch/core.py
gembatch/core_test.py
gembatch/eventarc.py
gembatch/firestore.indexes.json
gembatch/gemini.py
gembatch/health.py
gembatch/models.py
gembatch/tasks.py
gembatch/types.py
gembatch/utils.py
gembatch-0.1.6.dist-info/LICENSE
gembatch-0.1.6.dist-info/METADATA
gembatch-0.1.6.dist-info/WHEEL
gembatch-0.1.6.dist-info/entry_points.txt
gembatch-0.1.6.dist-info/top_level.txt
gembatch-0.1.6.dist-info/RECORD
